abucodingai_smartgit-1.0.0.dist-info/licenses/LICENSE
smartgit/__init__.py
smartgit/cli.py
smartgit/smartgit.py
abucodingai_smartgit-1.0.0.dist-info/METADATA
abucodingai_smartgit-1.0.0.dist-info/WHEEL
abucodingai_smartgit-1.0.0.dist-info/entry_points.txt
abucodingai_smartgit-1.0.0.dist-info/top_level.txt
abucodingai_smartgit-1.0.0.dist-info/RECORD
